torch_tensorrt/_C.cp313-win_amd64.pyd
torch_tensorrt/_Device.py
torch_tensorrt/_Input.py
torch_tensorrt/_TensorRTProxyModule.py
torch_tensorrt/__init__.py
torch_tensorrt/_compile.py
torch_tensorrt/_enums.py
torch_tensorrt/_features.py
torch_tensorrt/_utils.py
torch_tensorrt/_version.py
torch_tensorrt/logging.py
torch_tensorrt/dynamo/_DryRunTracker.py
torch_tensorrt/dynamo/_SourceIR.py
torch_tensorrt/dynamo/__init__.py
torch_tensorrt/dynamo/_compiler.py
torch_tensorrt/dynamo/_defaults.py
torch_tensorrt/dynamo/_engine_cache.py
torch_tensorrt/dynamo/_exporter.py
torch_tensorrt/dynamo/_refit.py
torch_tensorrt/dynamo/_settings.py
torch_tensorrt/dynamo/_tracer.py
torch_tensorrt/dynamo/observer.py
torch_tensorrt/dynamo/types.py
torch_tensorrt/dynamo/utils.py
torch_tensorrt/dynamo/backend/__init__.py
torch_tensorrt/dynamo/backend/backends.py
torch_tensorrt/dynamo/conversion/_ConversionContext.py
torch_tensorrt/dynamo/conversion/_ConverterRegistry.py
torch_tensorrt/dynamo/conversion/_TRTBuilderMonitor.py
torch_tensorrt/dynamo/conversion/_TRTInterpreter.py
torch_tensorrt/dynamo/conversion/__init__.py
torch_tensorrt/dynamo/conversion/_conversion.py
torch_tensorrt/dynamo/conversion/aten_ops_converters.py
torch_tensorrt/dynamo/conversion/converter_utils.py
torch_tensorrt/dynamo/conversion/custom_ops_converters.py
torch_tensorrt/dynamo/conversion/ops_evaluators.py
torch_tensorrt/dynamo/conversion/prims_ops_converters.py
torch_tensorrt/dynamo/conversion/truncate_double.py
torch_tensorrt/dynamo/conversion/impl/__init__.py
torch_tensorrt/dynamo/conversion/impl/addmm.py
torch_tensorrt/dynamo/conversion/impl/arange.py
torch_tensorrt/dynamo/conversion/impl/cast.py
torch_tensorrt/dynamo/conversion/impl/cat.py
torch_tensorrt/dynamo/conversion/impl/conv.py
torch_tensorrt/dynamo/conversion/impl/deconv.py
torch_tensorrt/dynamo/conversion/impl/dynamic_block_quantize.py
torch_tensorrt/dynamo/conversion/impl/embedding.py
torch_tensorrt/dynamo/conversion/impl/full.py
torch_tensorrt-2.9.0.dist-info/LICENSE
torch_tensorrt-2.9.0.dist-info/METADATA
torch_tensorrt-2.9.0.dist-info/WHEEL
torch_tensorrt-2.9.0.dist-info/top_level.txt
torch_tensorrt-2.9.0.dist-info/RECORD
