Metadata-Version: 2.1
Name: torch_tensorrt
Version: 2.9.0
Summary: Torch-TensorRT is a package which allows users to automatically compile PyTorch and TorchScript modules to TensorRT while remaining in PyTorch
Author-email: NVIDIA Corporation <narens@nvidia.com>
License: Copyright (c) 2020-present, NVIDIA CORPORATION. All rights reserved.
Project-URL: Homepage, https://pytorch.org/tensorrt
Project-URL: Documentation, https://pytorch.org/tensorrt
Project-URL: Repository, https://github.com/pytorch/tensorrt.git
Project-URL: Changelog, https://github.com/pytorch/tensorrt/releases
Keywords: pytorch,torch,tensorrt,trt,ai,artificial intelligence,ml,machine learning,dl,deep learning,compiler,dynamo,torchscript,inference
Classifier: Development Status :: 5 - Production/Stable
Classifier: Environment :: GPU :: NVIDIA CUDA
Classifier: License :: OSI Approved :: BSD License
Classifier: Intended Audience :: Developers
Classifier: Intended Audience :: Science/Research
Classifier: Operating System :: POSIX :: Linux
Classifier: Programming Language :: C++
Classifier: Programming Language :: Python
Classifier: Programming Language :: Python :: Implementation :: CPython
Classifier: Topic :: Scientific/Engineering
Classifier: Topic :: Scientific/Engineering :: Artificial Intelligence
Classifier: Topic :: Software Development
Classifier: Topic :: Software Development :: Libraries
Requires-Python: >=3.9
License-File: LICENSE
Requires-Dist: packaging >=23
Requires-Dist: typing-extensions >=4.7.0
Requires-Dist: dllist
Requires-Dist: numpy
Requires-Dist: torch <2.10.0,>=2.9.0
Requires-Dist: tensorrt <10.14.0,>=10.13.0
Requires-Dist: tensorrt-cu13 <10.14.0,>=10.13.0
Requires-Dist: tensorrt-cu13-bindings <10.14.0,>=10.13.0
Requires-Dist: tensorrt-cu13-libs <10.14.0,>=10.13.0
